kfinny
