Metadata-Version: 2.1
Name: kfinny.cachedvt
Version: 3.0.1
Summary: An extension of vt-py supporting local file cache
Home-page: https://github.com/kfinny/cached-virustotal-api
Author: Kevin Finnigin
Author-email: kevin@finnigin.net
License: MIT
Platform: UNKNOWN
